AUTHORS
CHANGES
COPYING
INSTALL
MANIFEST.in
README
setup.py
bin/domainmodel-admin
bin/domainmodel-makeconfig
bin/domainmodel-sdist-maker
bin/domainmodel-test
bin/migratedata-dump-standalone
src/dm/__init__.py
src/dm/accesscontrol.py
src/dm/accesscontroltest.py
src/dm/apachetest.py
src/dm/application.py
src/dm/applicationtest.py
src/dm/builder.py
src/dm/commandtest.py
src/dm/config.py
src/dm/configtest.py
src/dm/configwriter.py
src/dm/configwritertest.py
src/dm/datetimeconvertor.py
src/dm/datetimeconvertortest.py
src/dm/dbtest.py
src/dm/debug.py
src/dm/debugtest.py
src/dm/dictionary.py
src/dm/dictionarydef.py
src/dm/dictionarytest.py
src/dm/dictionarywords.py
src/dm/dictionarywordstest.py
src/dm/djangotest.py
src/dm/domtest.py
src/dm/environment.py
src/dm/environmenttest.py
src/dm/exceptions.py
src/dm/filesystem.py
src/dm/filesystemtest.py
src/dm/ioc.py
src/dm/ioctest.py
src/dm/log.py
src/dm/logtest.py
src/dm/messagedigest.py
src/dm/migrate.py
src/dm/migratetest.py
src/dm/mode.py
src/dm/on.py
src/dm/plugintest.py
src/dm/pylonstest.py
src/dm/regexps.py
src/dm/soleInstance.py
src/dm/strategy.py
src/dm/strategytest.py
src/dm/test.py
src/dm/testbase.py
src/dm/testrunner.py
src/dm/testunit.py
src/dm/timepoint.py
src/dm/timepointtest.py
src/dm/times.py
src/dm/timestest.py
src/dm/utiltest.py
src/dm/viewtest.py
src/dm/webkittest.py
src/dm/apache/__init__.py
src/dm/apache/config.py
src/dm/apache/configtest.py
src/dm/cli/__init__.py
src/dm/cli/admin.py
src/dm/cli/base.py
src/dm/cli/makeconfig.py
src/dm/cli/test.py
src/dm/command/__init__.py
src/dm/command/accesscontrol.py
src/dm/command/accesscontroltest.py
src/dm/command/base.py
src/dm/command/captcha.py
src/dm/command/emailbase.py
src/dm/command/emailpassword.py
src/dm/command/emailpasswordtest.py
src/dm/command/initialise.py
src/dm/command/person.py
src/dm/command/persontest.py
src/dm/command/plugin.py
src/dm/command/plugintest.py
src/dm/command/role.py
src/dm/command/state.py
src/dm/command/statetest.py
src/domainmodel.egg-info/PKG-INFO
src/domainmodel.egg-info/SOURCES.txt
src/domainmodel.egg-info/dependency_links.txt
src/domainmodel.egg-info/not-zip-safe
src/domainmodel.egg-info/requires.txt
src/domainmodel.egg-info/top_level.txt