Metadata-Version: 1.1
Name: domainmodel
Version: 0.15
Summary: Toolkit for domain model-based enterprise application frameworks.
Home-page: http://appropriatesoftware.net/domainmodel/Home.html
Author: Appropriate Software Foundation, Open Knowledge Foundation
Author-email: kforge-dev@lists.okfn.org
License: AGPL
Platform: UNKNOWN
Classifier: Development Status :: 5 - Production/Stable
Classifier: Environment :: Console
Classifier: Environment :: Web Environment
Classifier: Intended Audience :: Developers
Classifier: License :: OSI Approved :: GNU Affero General Public License v3
Classifier: Operating System :: OS Independent
Classifier: Programming Language :: Python
Classifier: Topic :: Software Development :: Libraries :: Python Modules
